pdf_reader_mcp/__init__.py
pdf_reader_mcp/cli.py
pdf_reader_mcp/server.py
pdf_reader_mcp-0.1.1.dist-info/METADATA
pdf_reader_mcp-0.1.1.dist-info/WHEEL
pdf_reader_mcp-0.1.1.dist-info/entry_points.txt
pdf_reader_mcp-0.1.1.dist-info/licenses/LICENSE
pdf_reader_mcp-0.1.1.dist-info/RECORD
