Metadata-Version: 2.4
Name: pdf-reader-mcp
Version: 0.1.1
Summary: A powerful MCP server for comprehensive PDF processing with OCR and diagram detection
Project-URL: Homepage, https://github.com/zixma13/pdf-reader-mcp
Project-URL: Repository, https://github.com/zixma13/pdf-reader-mcp.git
Project-URL: Issues, https://github.com/zixma13/pdf-reader-mcp/issues
Project-URL: Changelog, https://github.com/zixma13/pdf-reader-mcp/blob/main/CHANGELOG.md
Project-URL: Documentation, https://github.com/zixma13/pdf-reader-mcp#readme
Author-email: Apisak Musikapan <apisak13@gmail.com>
Maintainer-email: Apisak Musikapan <apisak13@gmail.com>
License: MIT
License-File: LICENSE
Keywords: mcp,ocr,pdf,text-extraction
Classifier: Development Status :: 4 - Beta
Classifier: Environment :: Console
Classifier: Intended Audience :: Developers
Classifier: License :: OSI Approved :: MIT License
Classifier: Operating System :: OS Independent
Classifier: Programming Language :: Python :: 3
Classifier: Programming Language :: Python :: 3.11
Classifier: Programming Language :: Python :: 3.12
Classifier: Topic :: Multimedia :: Graphics :: Graphics Conversion
Classifier: Topic :: Software Development :: Libraries :: Python Modules
Classifier: Topic :: Text Processing :: General
Classifier: Typing :: Typed
Requires-Python: >=3.11
Requires-Dist: markdown>=3.4.3
Requires-Dist: mcp>=1.8.0
Requires-Dist: numpy>=1.24.0
Requires-Dist: opencv-python>=4.8.0
Requires-Dist: pdfkit>=1.0.0
Requires-Dist: pillow>=10.0.0
Requires-Dist: pymupdf>=1.22.5
Requires-Dist: pypdf2>=3.0.1
Requires-Dist: pytesseract>=0.3.13
Requires-Dist: requests>=2.31.0
Provides-Extra: dev
Requires-Dist: black>=23.0.0; extra == 'dev'
Requires-Dist: build>=0.10.0; extra == 'dev'
Requires-Dist: flake8>=6.0.0; extra == 'dev'
Requires-Dist: mypy>=1.0.0; extra == 'dev'
Requires-Dist: pytest-cov>=4.0.0; extra == 'dev'
Requires-Dist: pytest>=7.0.0; extra == 'dev'
Requires-Dist: twine>=4.0.0; extra == 'dev'
